iparrot/__init__.py
iparrot/parrot.py
iparrot/parser.py
iparrot/player.py
iparrot/extension/__init__.py
iparrot/extension/helper.py
iparrot/modules/__init__.py
iparrot/modules/helper.py
iparrot/modules/logger.py
iparrot/modules/reportor.py
iparrot/modules/request.py
iparrot/modules/validator.py
iParrot-1.1.5.dist-info/LICENSE
iParrot-1.1.5.dist-info/METADATA
iParrot-1.1.5.dist-info/WHEEL
iParrot-1.1.5.dist-info/entry_points.txt
iParrot-1.1.5.dist-info/top_level.txt
iParrot-1.1.5.dist-info/RECORD
