Metadata-Version: 2.1
Name: iParrot
Version: 1.1.5
Summary: Automated test solution for http requests based on recording and playback
Home-page: https://github.com/idle-man/iParrot
Author: idle-man
Author-email: i@idleman.club
License: MIT
Project-URL: Bug Reports, https://github.com/idle-man/iParrot/issues
Project-URL: Source, https://github.com/idle-man/iParrot
Project-URL: Documentation, https://github.com/idle-man/iParrot/blob/master/README.md
Keywords: test automate automation record replay playback parrot iparrot http
Platform: UNKNOWN
Classifier: Development Status :: 4 - Beta
Classifier: Intended Audience :: Developers
Classifier: Intended Audience :: Information Technology
Classifier: Intended Audience :: Other Audience
Classifier: Topic :: Scientific/Engineering
Classifier: Topic :: Software Development :: Testing
Classifier: Topic :: Software Development :: Libraries
Classifier: License :: OSI Approved :: MIT License
Classifier: Programming Language :: Python :: 3
Classifier: Programming Language :: Python :: 3.5
Classifier: Programming Language :: Python :: 3.6
Classifier: Programming Language :: Python :: 3.7
Classifier: Operating System :: OS Independent
Classifier: Operating System :: MacOS
Classifier: Operating System :: Microsoft :: Windows
Classifier: Operating System :: Unix
Requires-Python: >=3, !=3.0.*, !=3.1.*, !=3.2.*, !=3.3.*, !=3.4.*, <4
Requires-Dist: PyYAML
Requires-Dist: requests
Provides-Extra: dev
Requires-Dist: check-manifest ; extra == 'dev'
Provides-Extra: test
Requires-Dist: coverage ; extra == 'test'
